<?xml version="1.0"?>
<!DOCTYPE hibernate-mapping PUBLIC "-//Hibernate/Hibernate Mapping DTD 3.0//EN"
"http://hibernate.sourceforge.net/hibernate-mapping-3.0.dtd">
<!-- Generated 25 f?vr. 2014 12:11:47 by Hibernate Tools 3.4.0.CR1 -->
<hibernate-mapping>
    <class name="com.orbit.openx.model.Preferences" table="ox_preferences" >
        <id name="preferenceId" type="java.lang.Integer">
            <column name="preference_id" />
            <generator class="identity" />
        </id>
        <property name="preferenceName" type="string">
            <column name="preference_name" length="64" not-null="true" unique="true" />
        </property>
        <property name="accountType" type="string">
            <column name="account_type" length="16" not-null="true" />
        </property>
    </class>
</hibernate-mapping>
